{
  "parent": "extraores:amordrine",
  "criteria": {
    "angmallen": {
      "conditions": {
        "items": [
          {
            "items": [
              "extraores:rawangmallen"
            ]
          }
        ]
      },
      "trigger": "minecraft:inventory_changed"
    }
  },
  "display": {
    "announce_to_chat": true,
    "background": "minecraft:textures/gui/advancements/backgrounds/stone.png",
    "description": {
      "translate": "Mine Angmallen Ore"
    },
    "frame": "task",
    "hidden": false,
    "icon": {
      "item": "extraores:angmallenore"
    },
    "show_toast": true,
    "title": {
      "translate": "It's Angelic"
    }
  },
  "requirements": [
    [
      "angmallen"
    ]
  ],
  "sends_telemetry_event": true
}