{
  "parent": "extraores:oureclase",
  "criteria": {
    "promethium": {
      "conditions": {
        "items": [
          {
            "items": [
              "extraores:rawpromethium"
            ]
          }
        ]
      },
      "trigger": "minecraft:inventory_changed"
    }
  },
  "display": {
    "announce_to_chat": true,
    "background": "minecraft:textures/gui/advancements/backgrounds/stone.png",
    "description": {
      "translate": "Mine Promethium Ore"
    },
    "frame": "task",
    "hidden": false,
    "icon": {
      "item": "extraores:promethiumore"
    },
    "show_toast": true,
    "title": {
      "translate": "Prometheus Would Be Pleased"
    }
  },
  "requirements": [
    [
      "promethium"
    ]
  ],
  "sends_telemetry_event": true
}