{
  "parent": "minecraft:recipes/root",
  "criteria": {
    "atlarusingot": {
      "conditions": {
        "items": [
          {
            "items": [
              "extraores:atlarusingot"
            ]
          }
        ]
      },
      "trigger": "minecraft:inventory_changed"
    },
    "has_the_recipe": {
      "conditions": {
        "recipe": "extraores:atlarusingot"
      },
      "trigger": "minecraft:recipe_unlocked"
    }
  },
  "requirements": [
    [
      "atlarusingot",
      "has_the_recipe"
    ]
  ],
  "rewards": {
    "recipes": [
      "extraores:atlarusingot"
    ]
  }
}