{
  "parent": "minecraft:recipes/root",
  "criteria": {
    "has_the_recipe": {
      "conditions": {
        "recipe": "extraores:smeltthalliumore"
      },
      "trigger": "minecraft:recipe_unlocked"
    },
    "smeltthalliumore": {
      "conditions": {
        "items": [
          {
            "items": [
              "extraores:thalliumingot"
            ]
          }
        ]
      },
      "trigger": "minecraft:inventory_changed"
    }
  },
  "requirements": [
    [
      "smeltthalliumore",
      "has_the_recipe"
    ]
  ],
  "rewards": {
    "recipes": [
      "extraores:smeltthalliumore"
    ]
  },
  "sends_telemetry_event": false
}