{
  "parent": "minecraft:recipes/root",
  "rewards": {
    "recipes": [
      "extraores:cuttinore"
    ]
  },
  "criteria": {
    "cuttinore": {
      "trigger": "minecraft:inventory_changed",
      "conditions": {
        "items": [
          {
            "item": "extraores:tindust"
          }
        ]
      }
    },
    "has_the_recipe": {
      "trigger": "minecraft:recipe_unlocked",
      "conditions": {
        "recipe": "extraores:cuttinore"
      }
    }
  },
  "requirements": [
    [
      "cuttinore",
      "has_the_recipe"
    ]
  ]
}