{
  "parent": "minecraft:recipes/root",
  "rewards": {
    "recipes": [
      "extraores:enrichrheniumdirtydust"
    ]
  },
  "criteria": {
    "enrichrheniumdirtydust": {
      "trigger": "minecraft:inventory_changed",
      "conditions": {
        "items": [
          {
            "items": [
              "extraores:rheniumore"
            ]
          }
        ]
      }
    },
    "has_the_recipe": {
      "trigger": "minecraft:recipe_unlocked",
      "conditions": {
        "recipe": "extraores:enrichrheniumdirtydust"
      }
    }
  },
  "requirements": [
    [
      "enrichrheniumdirtydust",
      "has_the_recipe"
    ]
  ]
}