{
  "parent": "minecraft:recipes/root",
  "criteria": {
    "enrichpalladiumdirtydust": {
      "conditions": {
        "items": [
          {
            "items": [
              "extraores:palladiumore"
            ]
          }
        ]
      },
      "trigger": "minecraft:inventory_changed"
    },
    "has_the_recipe": {
      "conditions": {
        "recipe": "extraores:enrichpalladiumdirtydust"
      },
      "trigger": "minecraft:recipe_unlocked"
    }
  },
  "requirements": [
    [
      "enrichpalladiumdirtydust",
      "has_the_recipe"
    ]
  ],
  "rewards": {
    "recipes": [
      "extraores:enrichpalladiumdirtydust"
    ]
  }
}