{
  "parent": "minecraft:recipes/root",
  "criteria": {
    "has_the_recipe": {
      "conditions": {
        "recipe": "extraores:injectrawtartarite"
      },
      "trigger": "minecraft:recipe_unlocked"
    },
    "injectrawtartarite": {
      "conditions": {
        "items": [
          {
            "items": [
              "extraores:tartariteore"
            ]
          }
        ]
      },
      "trigger": "minecraft:inventory_changed"
    }
  },
  "requirements": [
    [
      "injectrawtartarite",
      "has_the_recipe"
    ]
  ],
  "rewards": {
    "recipes": [
      "extraores:injectrawtartarite"
    ]
  }
}