{
  "parent": "minecraft:recipes/root",
  "criteria": {
    "has_the_recipe": {
      "conditions": {
        "recipe": "extraores:injectrawruthenium"
      },
      "trigger": "minecraft:recipe_unlocked"
    },
    "injectrawruthenium": {
      "conditions": {
        "items": [
          {
            "items": [
              "extraores:rutheniumore"
            ]
          }
        ]
      },
      "trigger": "minecraft:inventory_changed"
    }
  },
  "requirements": [
    [
      "injectrawruthenium",
      "has_the_recipe"
    ]
  ],
  "rewards": {
    "recipes": [
      "extraores:injectrawruthenium"
    ]
  },
  "sends_telemetry_event": true
}