{
  "parent": "minecraft:recipes/root",
  "criteria": {
    "has_the_recipe": {
      "conditions": {
        "recipe": "extraores:purifyraweximite"
      },
      "trigger": "minecraft:recipe_unlocked"
    },
    "purifyraweximite": {
      "conditions": {
        "items": [
          {
            "items": [
              "extraores:raweximite"
            ]
          }
        ]
      },
      "trigger": "minecraft:inventory_changed"
    }
  },
  "requirements": [
    [
      "purifyraweximite",
      "has_the_recipe"
    ]
  ],
  "rewards": {
    "recipes": [
      "extraores:purifyraweximite"
    ]
  },
  "sends_telemetry_event": true
}